anvil/__init__.py
anvil/main.py
anvil/agent/brain.py
anvil/agent/graph.py
anvil/agent/llm.py
anvil/agent/prompts.py
anvil/core/env.py
anvil/core/graph.py
anvil/core/logging.py
anvil/core/models.py
anvil/core/scanner.py
anvil/core/upgrader.py
anvil/core/parsers/base.py
anvil/core/parsers/pyproject.py
anvil/core/parsers/requirements.py
anvil/retrievers/base.py
anvil/retrievers/github.py
anvil/retrievers/main.py
anvil/retrievers/pypi.py
anvil/tools/package.py
anvil/tools/runner.py
anvil/ui/dashboard.py
anvil_py-0.1.1.dist-info/METADATA
anvil_py-0.1.1.dist-info/WHEEL
anvil_py-0.1.1.dist-info/entry_points.txt
anvil_py-0.1.1.dist-info/licenses/LICENSE
anvil_py-0.1.1.dist-info/RECORD
