Metadata-Version: 2.4
Name: anvil-py
Version: 0.1.1
Summary: AI-powered agentic dependency manager that analyzes changelogs and safely upgrades packages.
Project-URL: Repository, https://github.com/akashbhat/anvil
Project-URL: Issues, https://github.com/akashbhat/anvil/issues
Author-email: Akash Bhat <akash@skylarkdrones.com>
License: MIT License
License-File: LICENSE
Keywords: agent,ai,automation,dependency-manager,forensics,llm,security,upgrade
Classifier: Development Status :: 4 - Beta
Classifier: Environment :: Console
Classifier: Intended Audience :: Developers
Classifier: License :: OSI Approved :: MIT License
Classifier: Programming Language :: Python :: 3.10
Classifier: Programming Language :: Python :: 3.11
Classifier: Programming Language :: Python :: 3.12
Classifier: Programming Language :: Python :: 3.13
Classifier: Topic :: Software Development :: Build Tools
Classifier: Topic :: Software Development :: Libraries :: Python Modules
Requires-Python: >=3.10
Requires-Dist: langchain-ollama>=0.2.0
Requires-Dist: langchain-openai>=0.1.0
Requires-Dist: langchain>=0.3.0
Requires-Dist: langgraph>=0.2.0
Requires-Dist: packaging>=23.0
Requires-Dist: pydantic>=2.0.0
Requires-Dist: requests>=2.30.0
Requires-Dist: rich>=13.0.0
Requires-Dist: textual>=0.50.0
Requires-Dist: tomli>=2.0.0
Requires-Dist: typer>=0.9.0
